quickconf/__init__.py
quickconf/_version.py
quickconf/core.py
quickconf-0.2.0a5.dist-info/LICENSE
quickconf-0.2.0a5.dist-info/METADATA
quickconf-0.2.0a5.dist-info/WHEEL
quickconf-0.2.0a5.dist-info/top_level.txt
quickconf-0.2.0a5.dist-info/RECORD
