Metadata-Version: 2.1
Name: quickconf
Version: 0.2.0a5
Summary: Simple and flexible TOML-file based configurations framework
Author-email: Kenneth Trelborg Vestergaard <mortencombat@fastmail.com>
Project-URL: Homepage, https://github.com/mortencombat/quickconf
Project-URL: Repository, https://github.com/mortencombat/quickconf
Keywords: configuration,settings,options,toml
Classifier: Development Status :: 3 - Alpha
Classifier: Intended Audience :: Developers
Classifier: Programming Language :: Python :: 3
Classifier: License :: OSI Approved :: MIT License
Classifier: Operating System :: OS Independent
Requires-Python: >=3.10
License-File: LICENSE
Requires-Dist: attrs
Requires-Dist: tomli (>=2.0) ; python_version < "3.11"
Provides-Extra: build
Requires-Dist: setuptools ; extra == 'build'
Requires-Dist: build ; extra == 'build'
Requires-Dist: wheel ; extra == 'build'
Requires-Dist: twine ; extra == 'build'
Provides-Extra: save
Requires-Dist: tomlkit (<1.0,>=0.12.1) ; extra == 'save'
Provides-Extra: test
Requires-Dist: pre-commit ; extra == 'test'
Requires-Dist: pytest ; extra == 'test'
Requires-Dist: pytest-cov ; extra == 'test'
